argparse_helper/__init__.py
argparse_helper-0.9.3.dist-info/LICENCE.md
argparse_helper-0.9.3.dist-info/METADATA
argparse_helper-0.9.3.dist-info/WHEEL
argparse_helper-0.9.3.dist-info/top_level.txt
argparse_helper-0.9.3.dist-info/RECORD
