Metadata-Version: 2.1
Name: argparse-helper
Version: 0.9.3
Summary: Yet another argparse helper: complex sub-command trees made simple
Home-page: https://github.com/jan-g/{name}
Author: jan grant 
Author-email: argparse-helper@ioctl.org
License: Apache License 2.0
Platform: UNKNOWN
